pyfair/__init__.py
pyfair/model/__init__.py
pyfair/model/meta_model.py
pyfair/model/model.py
pyfair/model/model_calc.py
pyfair/model/model_input.py
pyfair/model/model_node.py
pyfair/model/model_tree.py
pyfair/report/__init__.py
pyfair/report/base_curve.py
pyfair/report/base_report.py
pyfair/report/distribution.py
pyfair/report/exceedence.py
pyfair/report/simple_report.py
pyfair/report/tree_graph.py
pyfair/report/violin.py
pyfair/static/data_entry.xlsx
pyfair/static/fair.css
pyfair/static/simple.html
pyfair/static/white_python_logo.png
pyfair/utility/__init__.py
pyfair/utility/beta_pert.py
pyfair/utility/database.py
pyfair/utility/factory.py
pyfair/utility/fair_exception.py
pyfair-0.1a13.dist-info/LICENSE
pyfair-0.1a13.dist-info/METADATA
pyfair-0.1a13.dist-info/WHEEL
pyfair-0.1a13.dist-info/top_level.txt
pyfair-0.1a13.dist-info/RECORD
