Metadata-Version: 2.1
Name: pyfair
Version: 0.1a13
Summary: Open FAIR Monte Carlo creator
Home-page: https://github.com/Hive-Systems/pyfair
Author: Hive Systems
Author-email: pyfair@hivesystems.com
License: MIT
Keywords: FAIR,risk,monte carlo,cyber risk,risk analysis
Classifier: Development Status :: 3 - Alpha
Classifier: License :: OSI Approved :: MIT License
Classifier: Programming Language :: Python :: 3
Classifier: Topic :: Security
Classifier: Topic :: Scientific/Engineering :: Mathematics
Requires-Python: >=3.6
License-File: LICENSE
Requires-Dist: pandas
Requires-Dist: numpy
Requires-Dist: scipy
Requires-Dist: matplotlib
Requires-Dist: xlrd
